.gitignore
LICENSE
MANIFEST.in
README.md
contributing.md
pyproject.toml
setup.cfg
setup.py
tox.ini
docs/.DS_Store
docs/Makefile
docs/conf.py
docs/index.rst
docs/make.bat
docs/riroriro/detectabilityfuns.rst
docs/riroriro/gwexporter.rst
docs/riroriro/horizondistfuns.rst
docs/riroriro/index.rst
docs/riroriro/inspiralfuns.rst
docs/riroriro/matchingfuns.rst
docs/riroriro/mergerfirstfuns.rst
docs/riroriro/mergersecondfuns.rst
docs/riroriro/snrcalculatorfuns.rst
docs/riroriro/tests.rst
licenses/LICENSE.rst
licenses/README.rst
licenses/TEMPLATE_LICENCE.rst
paper/paper.bib
paper/paper.md
paper/paper.pdf
riroriro/__init__.py
riroriro/_astropy_init.py
riroriro/detectabilityfuns.py
riroriro/gwexporter.py
riroriro/horizondistfuns.py
riroriro/inspiralfuns.py
riroriro/matchingfuns.py
riroriro/mergerfirstfuns.py
riroriro/mergersecondfuns.py
riroriro/snrcalculatorfuns.py
riroriro.egg-info/PKG-INFO
riroriro.egg-info/SOURCES.txt
riroriro.egg-info/dependency_links.txt
riroriro.egg-info/entry_points.txt
riroriro.egg-info/not-zip-safe
riroriro.egg-info/requires.txt
riroriro.egg-info/top_level.txt
riroriro/tests/test_detectabilityfuns.py
riroriro/tests/test_horizondistfuns.py
riroriro/tests/test_inspiralfuns.py
riroriro/tests/test_matchingfuns.py
riroriro/tests/test_mergerfirstfuns.py
riroriro/tests/test_mergersecondfuns.py
riroriro/tests/test_snrcalculatorfuns.py