Metadata-Version: 2.1
Name: riroriro
Version: 1.0.0
Summary: A code for simulating gravitational waves and evaluating their detectability.
Home-page: https://github.com/wvanzeist/riroriro
Author: Wouter van Zeist
Author-email: wvan478@aucklanduni.ac.nz
License: BSD 3-Clause
Platform: UNKNOWN
Requires-Python: >=3.6
Provides-Extra: test
Provides-Extra: docs
